Metadata-Version: 2.1
Name: xyzspaces
Version: 0.7.2
Summary: Manage your XYZ Hub server or HERE Data Hub from Python
Home-page: https://github.com/heremaps/xyz-spaces-python
Author: HERE Europe B.V.
Author-email: XYZSPACES_PYTHON_SUPPORT@here.com
License: Apache-2.0
Project-URL: Bug Tracker, https://github.com/heremaps/xyz-spaces-python/issues
Project-URL: Source, https://github.com/heremaps/xyz-spaces-python
Keywords: XYZ,API,REST,Client,Geospatial
Platform: any
Classifier: Development Status :: 4 - Beta
Classifier: Intended Audience :: Developers
Classifier: Topic :: Software Development :: Libraries
Classifier: License :: OSI Approved :: Apache Software License
Classifier: Operating System :: OS Independent
Classifier: Programming Language :: Python :: 3
Classifier: Programming Language :: Python :: 3 :: Only
Classifier: Programming Language :: Python :: 3.7
Classifier: Programming Language :: Python :: 3.8
Classifier: Programming Language :: Python :: 3.9
Requires-Dist: backoff (>=1.10.0)
Requires-Dist: geojson
Requires-Dist: requests
Requires-Dist: ijson (>=3.1.1)
Requires-Dist: pyhocon
Requires-Dist: requests-oauthlib
Provides-Extra: dev
Requires-Dist: black ; extra == 'dev'
Requires-Dist: codecov ; extra == 'dev'
Requires-Dist: coverage ; extra == 'dev'
Requires-Dist: mypy ; extra == 'dev'
Requires-Dist: proclamation ; extra == 'dev'
Requires-Dist: proxy.py ; extra == 'dev'
Requires-Dist: pytest (>=5.4.3) ; extra == 'dev'
Requires-Dist: pytest-cov ; extra == 'dev'
Requires-Dist: pytest-mypy ; extra == 'dev'
Requires-Dist: pytest-rerunfailures ; extra == 'dev'
Requires-Dist: Sphinx (>=2.4.0) ; extra == 'dev'
Requires-Dist: sphinx-rtd-theme ; extra == 'dev'
Requires-Dist: sphinx-thebe (>=0.0.8) ; extra == 'dev'
Requires-Dist: sphinx-copybutton ; extra == 'dev'
Requires-Dist: twine ; extra == 'dev'
Requires-Dist: pytest-flake8 ; extra == 'dev'
Requires-Dist: isort ; extra == 'dev'
Requires-Dist: darglint ; extra == 'dev'
Requires-Dist: types-requests ; extra == 'dev'
Provides-Extra: geo
Requires-Dist: geopandas ; extra == 'geo'
Requires-Dist: turfpy (>=0.0.3) ; extra == 'geo'
Requires-Dist: geobuf ; extra == 'geo'
